pandasbox/__init__.py
pandasbox/constants.py
pandasbox/exceptions.py
pandasbox/globals.py
pandasbox/pandas_table.py
pandasbox/sqlite_table.py
pandasbox/utils.py
pandasbox-0.2.0.dist-info/LICENSE
pandasbox-0.2.0.dist-info/WHEEL
pandasbox-0.2.0.dist-info/METADATA
pandasbox-0.2.0.dist-info/RECORD
