Metadata-Version: 2.1
Name: pandasbox
Version: 0.2.0
Summary: 
Home-page: https://github.com/manimino/pandasbox/
Author: Theo Walker
Author-email: theo.ca.walker@gmail.com
Requires-Python: >=3.7,<4.0
Classifier: Programming Language :: Python :: 3
Classifier: Programming Language :: Python :: 3.10
Classifier: Programming Language :: Python :: 3.7
Classifier: Programming Language :: Python :: 3.8
Classifier: Programming Language :: Python :: 3.9
Requires-Dist: pandas (>=1.0)
Project-URL: Documentation, https://pypi.org/project/pandasbox/
Project-URL: Repository, https://github.com/manimino/pandasbox/
